addmeta/__init__.py
addmeta/_version.py
addmeta/addmeta.py
addmeta/cli.py
addmeta_test1-0.post0.dev1.dist-info/licenses/LICENSE
addmeta_test1-0.post0.dev1.dist-info/METADATA
addmeta_test1-0.post0.dev1.dist-info/WHEEL
addmeta_test1-0.post0.dev1.dist-info/entry_points.txt
addmeta_test1-0.post0.dev1.dist-info/top_level.txt
addmeta_test1-0.post0.dev1.dist-info/RECORD
