Metadata-Version: 2.4
Name: addmeta-test1
Version: 0.post0.dev1
Summary: Add meta data to netCDF files.
Author-email: Aidan Heerdegen <aidan.heerdegen@anu.edu.au>, Tommy Gatti <tommy.gatti@anu.edu.au>, Davide Marchegiani <davide.marchegiani@anu.edu.au>
Maintainer-email: Aidan Heerdegen <aidan.heerdegen@anu.edu.au>
License-Expression: Apache-2.0
Project-URL: Repository, https://github.com/ACCESS-NRI/addmeta
Keywords: ACCESS-NRI,netcdf,metadata
Requires-Python: >=3.9
License-File: LICENSE
Requires-Dist: netcdf4
Requires-Dist: pyyaml
Provides-Extra: dev
Requires-Dist: coverage; extra == "dev"
Requires-Dist: codecov; extra == "dev"
Requires-Dist: six; extra == "dev"
Requires-Dist: pytest-cov; extra == "dev"
Requires-Dist: pytest; extra == "dev"
Dynamic: license-file
